Workbook

Sheet 🚀 Welcome
B2: Drink COGS Calculator
B3: Coffee Shop Basecamp · Week 4 · Menu Design & Coffee Program
B4: Timberline Coffee School
B7: HOW TO USE THIS CALCULATOR
B8: Step 1 — Ingredient Prices
B9: Go to the '💰 Ingredient Prices' tab. Enter what you actually pay for each ingredient — coffee per kg, each milk type per litre, syrups, cups, lids. These are the only numbers you need to enter on that tab.
B11: Step 2 — Drink Builder
B12: Go to the '☕ Drink Builder' tab. For each drink on your menu, enter the name, number of shots, milk type, milk volume, syrup pumps, cup size, and whether you use a sleeve. The cost per drink calculates automatically.
B14: Step 3 — Menu Summary
B15: Go to the '📊 Menu Summary' tab. Your drink costs will pull through automatically. Add your planned selling price for each drink — the tab calculates your margin per drink and your blended menu margin.
B17: Step 4 — Feed into Menu Builder
B18: Copy the 'Cost per drink' and 'Margin %' columns from the Menu Summary tab into your Week 4 Menu Builder worksheet. Your numbers are now real — not guesses.
B21: COLOUR & FORMATTING LEGEND
B22: Blue text on light teal | C22: Cells you fill in — your ingredient costs, quantities, and prices
B23: Blue text on yellow | C23: Key inputs that drive most of the calculation — pay attention to these
B24: Black text | C24: Calculated values — the spreadsheet works these out for you. Don't edit.
B25: Green text on grey | C25: Values pulled automatically from another tab in this workbook
B27: A NOTE ON THE NUMBERS
B28: The ingredient costs in this calculator are estimates based on typical wholesale rates. Your actual costs will vary depending on your roaster, your milk supplier, your cup supplier, and your location. The default values give you a realistic starting point — but replace them with your real numbers as soon as you have them. Real numbers make real models. Guesses make plans that fall apart.

Sheet 💰 Ingredient Prices
B2: Ingredient Prices
B3: Enter what you actually pay for each ingredient. These prices flow automatically into the Drink Builder.
B4: Blue cells = your inputs | Black cells = calculated automatically
B6: A — COFFEE
B7: Ingredient | C7: Your Cost | D7: Unit | E7: Yield / Dose | F7: Cost Per Shot / Cup
B8: Espresso blend (house) | C8: 14 | D8: per kg | E8: 18 | F8: g per double shot
B9: Single origin / filter | C9: 18 | D9: per kg | E9: 15 | F9: g per cup (batch)
B10: Decaf blend | C10: 16 | D10: per kg | E10: 18 | F10: g per double shot
B11: → Cost per double shot (house espresso) | C11: =C8/1000*E8*1.15 -> 0.2898 | D11: Includes 15% waste factor for grinding & bad shots
B12: → Cost per filter cup (batch brew) | C12: =C9/1000*E9*1.1 -> 0.297 | D12: Includes 10% waste factor for batch brew
B14: B — MILK & ALTERNATIVES
B15: Milk Type | C15: Cost per Litre | D15: Unit | E15: Markup vs Dairy | F15: Notes
B16: Whole milk (dairy) | C16: 1.2 | D16: per litre | E16: =IF(C16=C16,"-",TEXT(C16/C16-1,"0%")&" more than dairy") -> - | F16: Your baseline — most drinks
B17: Oat milk | C17: 2.8 | D17: per litre | E17: =IF(C17=C16,"-",TEXT(C17/C16-1,"0%")&" more than dairy") -> 133% more than dairy | F17: Most popular alt-milk; charge $0.75–$1.00 extra
B18: Almond milk | C18: 2.5 | D18: per litre | E18: =IF(C18=C16,"-",TEXT(C18/C16-1,"0%")&" more than dairy") -> 108% more than dairy | F18: Thinner texture; charge $0.75 extra
B19: Soy milk | C19: 2.2 | D19: per litre | E19: =IF(C19=C16,"-",TEXT(C19/C16-1,"0%")&" more than dairy") -> 83% more than dairy | F19: Older alt-milk; declining demand
B20: Coconut milk | C20: 2.6 | D20: per litre | E20: =IF(C20=C16,"-",TEXT(C20/C16-1,"0%")&" more than dairy") -> 117% more than dairy | F20: Good for iced drinks and specialty
B21: → Cost per 180ml dairy (flat white / latte portion) | C21: =C16/1000*180 -> 0.216 | D21: 180ml = standard flat white / medium latte milk volume
B22: → Cost per 180ml oat milk (flat white / latte portion) | C22: =C17/1000*180 -> 0.504 | D22: This is why oat milk surcharges matter — it costs ~2x more per drink
B24: C — SYRUPS & FLAVOURINGS
B25: Ingredient | C25: Cost per Litre / Unit | D25: Pumps per Litre | E25: Cost per Pump | F25: Notes
B26: Flavoured syrup (vanilla, caramel, etc.) | C26: 18 | D26: 100 | E26: =C26/D26 -> 0.18 | F26: ~10ml per pump; 1 pump per standard flavoured drink
B27: Simple syrup (house-made) | C27: 4 | D27: 100 | E27: =C27/D27 -> 0.04 | F27: Cheap to make; good for iced drinks
B28: Matcha powder | C28: 28 | D28: — | E28: See note → | F28: Per 100g tin; ~5g per drink = price/100×5
B29: Chai concentrate | C29: 12 | D29: — | E29: See note → | F29: Per litre; ~60ml per chai latte
B30: Chocolate powder / cocoa | C30: 14 | D30: — | E30: See note → | F30: Per kg; ~15g per mocha
B31: Vanilla extract | C31: 22 | D31: — | E31: See note → | F31: Per litre; tiny quantities per drink
B33: D — CUPS, LIDS & PACKAGING
B34: Item | C34: Cost per Unit | D34: Unit | E34: Tip
B35: Small cup (4–6oz / espresso / cortado) | C35: 0.12 | D35: per cup | E35: Buy in cases of 1000 — unit cost drops significantly
B36: Medium cup (8–12oz / flat white / latte) | C36: 0.14 | D36: per cup | E36: Your highest-volume cup — negotiate the best rate here
B37: Large cup (16oz / big latte / cold) | C37: 0.16 | D37: per cup | E37: Use for iced drinks and large format orders
B38: Hot lid | C38: 0.06 | D38: per lid | E38: Always pair with hot cups
B39: Cold lid / dome lid | C39: 0.08 | D39: per lid | E39: For cold and blended drinks
B40: Sleeve / heat sleeve | C40: 0.05 | D40: per sleeve | E40: Only needed for hot drinks — not every customer takes one
B41: Straw (paper) | C41: 0.04 | D41: per straw | E41: For cold drinks; paper costs more than plastic
B42: Takeaway bag (for food) | C42: 0.1 | D42: per bag | E42: Only if you're offering food — include in food cost
B44: E — OTHER INGREDIENTS (add your own)
B45: Ingredient | C45: Cost | D45: Unit | E45: Cost per use | F45: Notes

Sheet ☕ Drink Builder
B2: Drink Builder
B3: Fill in the blue cells for each drink. The cost per drink calculates automatically from your Ingredient Prices tab.
B4: Blue = your inputs | Black = calculated | Green = pulled from Ingredient Prices tab
B6: Shots: enter 1 or 2 (most drinks are 2). Milk type: enter exactly — Dairy / Oat / Almond / Soy / Coconut / None. Milk vol (ml): 60 = macchiato, 120 = cortado, 180 = flat white, 240 = latte, 300 = large latte. Syrup pumps: 0 if none, 1–2 for flavoured drinks. Cup: Small / Medium / Large. Sleeve: Y or N.
B7: Drink Name | C7: Shots (1 or 2) | D7: Milk Type (Dairy/Oat/etc) | E7: Milk Vol (ml) | F7: Syrup Pumps | G7: Cup Size (S/M/L) | H7: Sleeve? (Y/N) | I7: Other Cost ($) | J7: Total Cost per Drink ($)
B8: Espresso (single) | C8: 1 | D8: None | F8: 0 | G8: Small | H8: N | J8: =IF(B8="","",(IF(OR(B8="Batch brew / drip",B8="Cold brew"),'💰 Ingredient Prices'!C12,IF(C8="",0,C8)*'💰 Ingredient Prices'!C11))+(IF(D8="None",0,IF(D8="Dairy",'💰 Ingredient Prices'!C16/1000*IF(E8="",0,E8),IF(D8="Oat",'💰 Ingredient Prices'!C17/1000*IF(E8="",0,E8),IF(D8="Almond",'💰 Ingredient Prices'!C18/1000*IF(E8="",0,E8),IF(D8="Soy",'💰 Ingredient Prices'!C19/1000*IF(E8="",0,E8),IF(D8="Coconut",'💰 Ingredient Prices'!C20/1000*IF(E8="",0,E8),0)))))))+IF(F8="",0,F8)*'💰 Ingredient Prices'!E26+(IF(G8="Small",'💰 Ingredient Prices'!C35+'💰 Ingredient Prices'!C38,IF(G8="Medium",'💰 Ingredient Prices'!C36+'💰 Ingredient Prices'!C38,IF(G8="Large",'💰 Ingredient Prices'!C37+'💰 Ingredient Prices'!C38,0)))+IF(H8="Y",'💰 Ingredient Prices'!C40,0))+IF(I8="",0,I8)) -> 0.4698
B9: Double espresso | C9: 2 | D9: None | F9: 0 | G9: Small | H9: N | J9: =IF(B9="","",(IF(OR(B9="Batch brew / drip",B9="Cold brew"),'💰 Ingredient Prices'!C12,IF(C9="",0,C9)*'💰 Ingredient Prices'!C11))+(IF(D9="None",0,IF(D9="Dairy",'💰 Ingredient Prices'!C16/1000*IF(E9="",0,E9),IF(D9="Oat",'💰 Ingredient Prices'!C17/1000*IF(E9="",0,E9),IF(D9="Almond",'💰 Ingredient Prices'!C18/1000*IF(E9="",0,E9),IF(D9="Soy",'💰 Ingredient Prices'!C19/1000*IF(E9="",0,E9),IF(D9="Coconut",'💰 Ingredient Prices'!C20/1000*IF(E9="",0,E9),0)))))))+IF(F9="",0,F9)*'💰 Ingredient Prices'!E26+(IF(G9="Small",'💰 Ingredient Prices'!C35+'💰 Ingredient Prices'!C38,IF(G9="Medium",'💰 Ingredient Prices'!C36+'💰 Ingredient Prices'!C38,IF(G9="Large",'💰 Ingredient Prices'!C37+'💰 Ingredient Prices'!C38,0)))+IF(H9="Y",'💰 Ingredient Prices'!C40,0))+IF(I9="",0,I9)) -> 0.7596
B10: Macchiato | C10: 2 | D10: Dairy | E10: 30 | F10: 0 | G10: Small | H10: N | J10: =IF(B10="","",(IF(OR(B10="Batch brew / drip",B10="Cold brew"),'💰 Ingredient Prices'!C12,IF(C10="",0,C10)*'💰 Ingredient Prices'!C11))+(IF(D10="None",0,IF(D10="Dairy",'💰 Ingredient Prices'!C16/1000*IF(E10="",0,E10),IF(D10="Oat",'💰 Ingredient Prices'!C17/1000*IF(E10="",0,E10),IF(D10="Almond",'💰 Ingredient Prices'!C18/1000*IF(E10="",0,E10),IF(D10="Soy",'💰 Ingredient Prices'!C19/1000*IF(E10="",0,E10),IF(D10="Coconut",'💰 Ingredient Prices'!C20/1000*IF(E10="",0,E10),0)))))))+IF(F10="",0,F10)*'💰 Ingredient Prices'!E26+(IF(G10="Small",'💰 Ingredient Prices'!C35+'💰 Ingredient Prices'!C38,IF(G10="Medium",'💰 Ingredient Prices'!C36+'💰 Ingredient Prices'!C38,IF(G10="Large",'💰 Ingredient Prices'!C37+'💰 Ingredient Prices'!C38,0)))+IF(H10="Y",'💰 Ingredient Prices'!C40,0))+IF(I10="",0,I10)) -> 0.7956
B11: Cortado | C11: 2 | D11: Dairy | E11: 60 | F11: 0 | G11: Small | H11: N | J11: =IF(B11="","",(IF(OR(B11="Batch brew / drip",B11="Cold brew"),'💰 Ingredient Prices'!C12,IF(C11="",0,C11)*'💰 Ingredient Prices'!C11))+(IF(D11="None",0,IF(D11="Dairy",'💰 Ingredient Prices'!C16/1000*IF(E11="",0,E11),IF(D11="Oat",'💰 Ingredient Prices'!C17/1000*IF(E11="",0,E11),IF(D11="Almond",'💰 Ingredient Prices'!C18/1000*IF(E11="",0,E11),IF(D11="Soy",'💰 Ingredient Prices'!C19/1000*IF(E11="",0,E11),IF(D11="Coconut",'💰 Ingredient Prices'!C20/1000*IF(E11="",0,E11),0)))))))+IF(F11="",0,F11)*'💰 Ingredient Prices'!E26+(IF(G11="Small",'💰 Ingredient Prices'!C35+'💰 Ingredient Prices'!C38,IF(G11="Medium",'💰 Ingredient Prices'!C36+'💰 Ingredient Prices'!C38,IF(G11="Large",'💰 Ingredient Prices'!C37+'💰 Ingredient Prices'!C38,0)))+IF(H11="Y",'💰 Ingredient Prices'!C40,0))+IF(I11="",0,I11)) -> 0.8316
B12: Flat white | C12: 2 | D12: Dairy | E12: 180 | F12: 0 | G12: Medium | H12: Y | J12: =IF(B12="","",(IF(OR(B12="Batch brew / drip",B12="Cold brew"),'💰 Ingredient Prices'!C12,IF(C12="",0,C12)*'💰 Ingredient Prices'!C11))+(IF(D12="None",0,IF(D12="Dairy",'💰 Ingredient Prices'!C16/1000*IF(E12="",0,E12),IF(D12="Oat",'💰 Ingredient Prices'!C17/1000*IF(E12="",0,E12),IF(D12="Almond",'💰 Ingredient Prices'!C18/1000*IF(E12="",0,E12),IF(D12="Soy",'💰 Ingredient Prices'!C19/1000*IF(E12="",0,E12),IF(D12="Coconut",'💰 Ingredient Prices'!C20/1000*IF(E12="",0,E12),0)))))))+IF(F12="",0,F12)*'💰 Ingredient Prices'!E26+(IF(G12="Small",'💰 Ingredient Prices'!C35+'💰 Ingredient Prices'!C38,IF(G12="Medium",'💰 Ingredient Prices'!C36+'💰 Ingredient Prices'!C38,IF(G12="Large",'💰 Ingredient Prices'!C37+'💰 Ingredient Prices'!C38,0)))+IF(H12="Y",'💰 Ingredient Prices'!C40,0))+IF(I12="",0,I12)) -> 1.0456
B13: Flat white (oat milk) | C13: 2 | D13: Oat | E13: 180 | F13: 0 | G13: Medium | H13: Y | J13: =IF(B13="","",(IF(OR(B13="Batch brew / drip",B13="Cold brew"),'💰 Ingredient Prices'!C12,IF(C13="",0,C13)*'💰 Ingredient Prices'!C11))+(IF(D13="None",0,IF(D13="Dairy",'💰 Ingredient Prices'!C16/1000*IF(E13="",0,E13),IF(D13="Oat",'💰 Ingredient Prices'!C17/1000*IF(E13="",0,E13),IF(D13="Almond",'💰 Ingredient Prices'!C18/1000*IF(E13="",0,E13),IF(D13="Soy",'💰 Ingredient Prices'!C19/1000*IF(E13="",0,E13),IF(D13="Coconut",'💰 Ingredient Prices'!C20/1000*IF(E13="",0,E13),0)))))))+IF(F13="",0,F13)*'💰 Ingredient Prices'!E26+(IF(G13="Small",'💰 Ingredient Prices'!C35+'💰 Ingredient Prices'!C38,IF(G13="Medium",'💰 Ingredient Prices'!C36+'💰 Ingredient Prices'!C38,IF(G13="Large",'💰 Ingredient Prices'!C37+'💰 Ingredient Prices'!C38,0)))+IF(H13="Y",'💰 Ingredient Prices'!C40,0))+IF(I13="",0,I13)) -> 1.3336
B14: Cappuccino | C14: 2 | D14: Dairy | E14: 180 | F14: 0 | G14: Medium | H14: Y | J14: =IF(B14="","",(IF(OR(B14="Batch brew / drip",B14="Cold brew"),'💰 Ingredient Prices'!C12,IF(C14="",0,C14)*'💰 Ingredient Prices'!C11))+(IF(D14="None",0,IF(D14="Dairy",'💰 Ingredient Prices'!C16/1000*IF(E14="",0,E14),IF(D14="Oat",'💰 Ingredient Prices'!C17/1000*IF(E14="",0,E14),IF(D14="Almond",'💰 Ingredient Prices'!C18/1000*IF(E14="",0,E14),IF(D14="Soy",'💰 Ingredient Prices'!C19/1000*IF(E14="",0,E14),IF(D14="Coconut",'💰 Ingredient Prices'!C20/1000*IF(E14="",0,E14),0)))))))+IF(F14="",0,F14)*'💰 Ingredient Prices'!E26+(IF(G14="Small",'💰 Ingredient Prices'!C35+'💰 Ingredient Prices'!C38,IF(G14="Medium",'💰 Ingredient Prices'!C36+'💰 Ingredient Prices'!C38,IF(G14="Large",'💰 Ingredient Prices'!C37+'💰 Ingredient Prices'!C38,0)))+IF(H14="Y",'💰 Ingredient Prices'!C40,0))+IF(I14="",0,I14)) -> 1.0456
B15: Latte | C15: 2 | D15: Dairy | E15: 240 | F15: 0 | G15: Medium | H15: Y | J15: =IF(B15="","",(IF(OR(B15="Batch brew / drip",B15="Cold brew"),'💰 Ingredient Prices'!C12,IF(C15="",0,C15)*'💰 Ingredient Prices'!C11))+(IF(D15="None",0,IF(D15="Dairy",'💰 Ingredient Prices'!C16/1000*IF(E15="",0,E15),IF(D15="Oat",'💰 Ingredient Prices'!C17/1000*IF(E15="",0,E15),IF(D15="Almond",'💰 Ingredient Prices'!C18/1000*IF(E15="",0,E15),IF(D15="Soy",'💰 Ingredient Prices'!C19/1000*IF(E15="",0,E15),IF(D15="Coconut",'💰 Ingredient Prices'!C20/1000*IF(E15="",0,E15),0)))))))+IF(F15="",0,F15)*'💰 Ingredient Prices'!E26+(IF(G15="Small",'💰 Ingredient Prices'!C35+'💰 Ingredient Prices'!C38,IF(G15="Medium",'💰 Ingredient Prices'!C36+'💰 Ingredient Prices'!C38,IF(G15="Large",'💰 Ingredient Prices'!C37+'💰 Ingredient Prices'!C38,0)))+IF(H15="Y",'💰 Ingredient Prices'!C40,0))+IF(I15="",0,I15)) -> 1.1176
B16: Latte (oat milk) | C16: 2 | D16: Oat | E16: 240 | F16: 0 | G16: Medium | H16: Y | J16: =IF(B16="","",(IF(OR(B16="Batch brew / drip",B16="Cold brew"),'💰 Ingredient Prices'!C12,IF(C16="",0,C16)*'💰 Ingredient Prices'!C11))+(IF(D16="None",0,IF(D16="Dairy",'💰 Ingredient Prices'!C16/1000*IF(E16="",0,E16),IF(D16="Oat",'💰 Ingredient Prices'!C17/1000*IF(E16="",0,E16),IF(D16="Almond",'💰 Ingredient Prices'!C18/1000*IF(E16="",0,E16),IF(D16="Soy",'💰 Ingredient Prices'!C19/1000*IF(E16="",0,E16),IF(D16="Coconut",'💰 Ingredient Prices'!C20/1000*IF(E16="",0,E16),0)))))))+IF(F16="",0,F16)*'💰 Ingredient Prices'!E26+(IF(G16="Small",'💰 Ingredient Prices'!C35+'💰 Ingredient Prices'!C38,IF(G16="Medium",'💰 Ingredient Prices'!C36+'💰 Ingredient Prices'!C38,IF(G16="Large",'💰 Ingredient Prices'!C37+'💰 Ingredient Prices'!C38,0)))+IF(H16="Y",'💰 Ingredient Prices'!C40,0))+IF(I16="",0,I16)) -> 1.5016
B17: Large latte | C17: 2 | D17: Dairy | E17: 300 | F17: 0 | G17: Large | H17: Y | J17: =IF(B17="","",(IF(OR(B17="Batch brew / drip",B17="Cold brew"),'💰 Ingredient Prices'!C12,IF(C17="",0,C17)*'💰 Ingredient Prices'!C11))+(IF(D17="None",0,IF(D17="Dairy",'💰 Ingredient Prices'!C16/1000*IF(E17="",0,E17),IF(D17="Oat",'💰 Ingredient Prices'!C17/1000*IF(E17="",0,E17),IF(D17="Almond",'💰 Ingredient Prices'!C18/1000*IF(E17="",0,E17),IF(D17="Soy",'💰 Ingredient Prices'!C19/1000*IF(E17="",0,E17),IF(D17="Coconut",'💰 Ingredient Prices'!C20/1000*IF(E17="",0,E17),0)))))))+IF(F17="",0,F17)*'💰 Ingredient Prices'!E26+(IF(G17="Small",'💰 Ingredient Prices'!C35+'💰 Ingredient Prices'!C38,IF(G17="Medium",'💰 Ingredient Prices'!C36+'💰 Ingredient Prices'!C38,IF(G17="Large",'💰 Ingredient Prices'!C37+'💰 Ingredient Prices'!C38,0)))+IF(H17="Y",'💰 Ingredient Prices'!C40,0))+IF(I17="",0,I17)) -> 1.2096
B18: Vanilla latte | C18: 2 | D18: Dairy | E18: 240 | F18: 1 | G18: Medium | H18: Y | J18: =IF(B18="","",(IF(OR(B18="Batch brew / drip",B18="Cold brew"),'💰 Ingredient Prices'!C12,IF(C18="",0,C18)*'💰 Ingredient Prices'!C11))+(IF(D18="None",0,IF(D18="Dairy",'💰 Ingredient Prices'!C16/1000*IF(E18="",0,E18),IF(D18="Oat",'💰 Ingredient Prices'!C17/1000*IF(E18="",0,E18),IF(D18="Almond",'💰 Ingredient Prices'!C18/1000*IF(E18="",0,E18),IF(D18="Soy",'💰 Ingredient Prices'!C19/1000*IF(E18="",0,E18),IF(D18="Coconut",'💰 Ingredient Prices'!C20/1000*IF(E18="",0,E18),0)))))))+IF(F18="",0,F18)*'💰 Ingredient Prices'!E26+(IF(G18="Small",'💰 Ingredient Prices'!C35+'💰 Ingredient Prices'!C38,IF(G18="Medium",'💰 Ingredient Prices'!C36+'💰 Ingredient Prices'!C38,IF(G18="Large",'💰 Ingredient Prices'!C37+'💰 Ingredient Prices'!C38,0)))+IF(H18="Y",'💰 Ingredient Prices'!C40,0))+IF(I18="",0,I18)) -> 1.2976
B19: Batch brew / drip | D19: None | F19: 0 | G19: Medium | H19: Y | J19: =IF(B19="","",(IF(OR(B19="Batch brew / drip",B19="Cold brew"),'💰 Ingredient Prices'!C12,IF(C19="",0,C19)*'💰 Ingredient Prices'!C11))+(IF(D19="None",0,IF(D19="Dairy",'💰 Ingredient Prices'!C16/1000*IF(E19="",0,E19),IF(D19="Oat",'💰 Ingredient Prices'!C17/1000*IF(E19="",0,E19),IF(D19="Almond",'💰 Ingredient Prices'!C18/1000*IF(E19="",0,E19),IF(D19="Soy",'💰 Ingredient Prices'!C19/1000*IF(E19="",0,E19),IF(D19="Coconut",'💰 Ingredient Prices'!C20/1000*IF(E19="",0,E19),0)))))))+IF(F19="",0,F19)*'💰 Ingredient Prices'!E26+(IF(G19="Small",'💰 Ingredient Prices'!C35+'💰 Ingredient Prices'!C38,IF(G19="Medium",'💰 Ingredient Prices'!C36+'💰 Ingredient Prices'!C38,IF(G19="Large",'💰 Ingredient Prices'!C37+'💰 Ingredient Prices'!C38,0)))+IF(H19="Y",'💰 Ingredient Prices'!C40,0))+IF(I19="",0,I19)) -> 0.547
B20: Cold brew | D20: None | F20: 0 | G20: Large | H20: N | J20: =IF(B20="","",(IF(OR(B20="Batch brew / drip",B20="Cold brew"),'💰 Ingredient Prices'!C12,IF(C20="",0,C20)*'💰 Ingredient Prices'!C11))+(IF(D20="None",0,IF(D20="Dairy",'💰 Ingredient Prices'!C16/1000*IF(E20="",0,E20),IF(D20="Oat",'💰 Ingredient Prices'!C17/1000*IF(E20="",0,E20),IF(D20="Almond",'💰 Ingredient Prices'!C18/1000*IF(E20="",0,E20),IF(D20="Soy",'💰 Ingredient Prices'!C19/1000*IF(E20="",0,E20),IF(D20="Coconut",'💰 Ingredient Prices'!C20/1000*IF(E20="",0,E20),0)))))))+IF(F20="",0,F20)*'💰 Ingredient Prices'!E26+(IF(G20="Small",'💰 Ingredient Prices'!C35+'💰 Ingredient Prices'!C38,IF(G20="Medium",'💰 Ingredient Prices'!C36+'💰 Ingredient Prices'!C38,IF(G20="Large",'💰 Ingredient Prices'!C37+'💰 Ingredient Prices'!C38,0)))+IF(H20="Y",'💰 Ingredient Prices'!C40,0))+IF(I20="",0,I20)) -> 0.517
B21: Iced latte | C21: 2 | D21: Dairy | E21: 180 | F21: 0 | G21: Large | H21: N | J21: =IF(B21="","",(IF(OR(B21="Batch brew / drip",B21="Cold brew"),'💰 Ingredient Prices'!C12,IF(C21="",0,C21)*'💰 Ingredient Prices'!C11))+(IF(D21="None",0,IF(D21="Dairy",'💰 Ingredient Prices'!C16/1000*IF(E21="",0,E21),IF(D21="Oat",'💰 Ingredient Prices'!C17/1000*IF(E21="",0,E21),IF(D21="Almond",'💰 Ingredient Prices'!C18/1000*IF(E21="",0,E21),IF(D21="Soy",'💰 Ingredient Prices'!C19/1000*IF(E21="",0,E21),IF(D21="Coconut",'💰 Ingredient Prices'!C20/1000*IF(E21="",0,E21),0)))))))+IF(F21="",0,F21)*'💰 Ingredient Prices'!E26+(IF(G21="Small",'💰 Ingredient Prices'!C35+'💰 Ingredient Prices'!C38,IF(G21="Medium",'💰 Ingredient Prices'!C36+'💰 Ingredient Prices'!C38,IF(G21="Large",'💰 Ingredient Prices'!C37+'💰 Ingredient Prices'!C38,0)))+IF(H21="Y",'💰 Ingredient Prices'!C40,0))+IF(I21="",0,I21)) -> 1.0156
B22: Matcha latte | D22: Dairy | E22: 240 | F22: 0 | G22: Medium | H22: Y | J22: =IF(B22="","",(IF(OR(B22="Batch brew / drip",B22="Cold brew"),'💰 Ingredient Prices'!C12,IF(C22="",0,C22)*'💰 Ingredient Prices'!C11))+(IF(D22="None",0,IF(D22="Dairy",'💰 Ingredient Prices'!C16/1000*IF(E22="",0,E22),IF(D22="Oat",'💰 Ingredient Prices'!C17/1000*IF(E22="",0,E22),IF(D22="Almond",'💰 Ingredient Prices'!C18/1000*IF(E22="",0,E22),IF(D22="Soy",'💰 Ingredient Prices'!C19/1000*IF(E22="",0,E22),IF(D22="Coconut",'💰 Ingredient Prices'!C20/1000*IF(E22="",0,E22),0)))))))+IF(F22="",0,F22)*'💰 Ingredient Prices'!E26+(IF(G22="Small",'💰 Ingredient Prices'!C35+'💰 Ingredient Prices'!C38,IF(G22="Medium",'💰 Ingredient Prices'!C36+'💰 Ingredient Prices'!C38,IF(G22="Large",'💰 Ingredient Prices'!C37+'💰 Ingredient Prices'!C38,0)))+IF(H22="Y",'💰 Ingredient Prices'!C40,0))+IF(I22="",0,I22)) -> 0.538
B23: Chai latte | D23: Dairy | E23: 240 | F23: 0 | G23: Medium | H23: Y | J23: =IF(B23="","",(IF(OR(B23="Batch brew / drip",B23="Cold brew"),'💰 Ingredient Prices'!C12,IF(C23="",0,C23)*'💰 Ingredient Prices'!C11))+(IF(D23="None",0,IF(D23="Dairy",'💰 Ingredient Prices'!C16/1000*IF(E23="",0,E23),IF(D23="Oat",'💰 Ingredient Prices'!C17/1000*IF(E23="",0,E23),IF(D23="Almond",'💰 Ingredient Prices'!C18/1000*IF(E23="",0,E23),IF(D23="Soy",'💰 Ingredient Prices'!C19/1000*IF(E23="",0,E23),IF(D23="Coconut",'💰 Ingredient Prices'!C20/1000*IF(E23="",0,E23),0)))))))+IF(F23="",0,F23)*'💰 Ingredient Prices'!E26+(IF(G23="Small",'💰 Ingredient Prices'!C35+'💰 Ingredient Prices'!C38,IF(G23="Medium",'💰 Ingredient Prices'!C36+'💰 Ingredient Prices'!C38,IF(G23="Large",'💰 Ingredient Prices'!C37+'💰 Ingredient Prices'!C38,0)))+IF(H23="Y",'💰 Ingredient Prices'!C40,0))+IF(I23="",0,I23)) -> 0.538
B24: Hot chocolate | D24: Dairy | E24: 240 | F24: 0 | G24: Medium | H24: Y | J24: =IF(B24="","",(IF(OR(B24="Batch brew / drip",B24="Cold brew"),'💰 Ingredient Prices'!C12,IF(C24="",0,C24)*'💰 Ingredient Prices'!C11))+(IF(D24="None",0,IF(D24="Dairy",'💰 Ingredient Prices'!C16/1000*IF(E24="",0,E24),IF(D24="Oat",'💰 Ingredient Prices'!C17/1000*IF(E24="",0,E24),IF(D24="Almond",'💰 Ingredient Prices'!C18/1000*IF(E24="",0,E24),IF(D24="Soy",'💰 Ingredient Prices'!C19/1000*IF(E24="",0,E24),IF(D24="Coconut",'💰 Ingredient Prices'!C20/1000*IF(E24="",0,E24),0)))))))+IF(F24="",0,F24)*'💰 Ingredient Prices'!E26+(IF(G24="Small",'💰 Ingredient Prices'!C35+'💰 Ingredient Prices'!C38,IF(G24="Medium",'💰 Ingredient Prices'!C36+'💰 Ingredient Prices'!C38,IF(G24="Large",'💰 Ingredient Prices'!C37+'💰 Ingredient Prices'!C38,0)))+IF(H24="Y",'💰 Ingredient Prices'!C40,0))+IF(I24="",0,I24)) -> 0.538
B25: Signature drink | C25: 2 | D25: Oat | E25: 180 | F25: 1 | G25: Medium | H25: Y | J25: =IF(B25="","",(IF(OR(B25="Batch brew / drip",B25="Cold brew"),'💰 Ingredient Prices'!C12,IF(C25="",0,C25)*'💰 Ingredient Prices'!C11))+(IF(D25="None",0,IF(D25="Dairy",'💰 Ingredient Prices'!C16/1000*IF(E25="",0,E25),IF(D25="Oat",'💰 Ingredient Prices'!C17/1000*IF(E25="",0,E25),IF(D25="Almond",'💰 Ingredient Prices'!C18/1000*IF(E25="",0,E25),IF(D25="Soy",'💰 Ingredient Prices'!C19/1000*IF(E25="",0,E25),IF(D25="Coconut",'💰 Ingredient Prices'!C20/1000*IF(E25="",0,E25),0)))))))+IF(F25="",0,F25)*'💰 Ingredient Prices'!E26+(IF(G25="Small",'💰 Ingredient Prices'!C35+'💰 Ingredient Prices'!C38,IF(G25="Medium",'💰 Ingredient Prices'!C36+'💰 Ingredient Prices'!C38,IF(G25="Large",'💰 Ingredient Prices'!C37+'💰 Ingredient Prices'!C38,0)))+IF(H25="Y",'💰 Ingredient Prices'!C40,0))+IF(I25="",0,I25)) -> 1.5136
J26: =IF(B26="","",(IF(OR(B26="Batch brew / drip",B26="Cold brew"),'💰 Ingredient Prices'!C12,IF(C26="",0,C26)*'💰 Ingredient Prices'!C11))+(IF(D26="None",0,IF(D26="Dairy",'💰 Ingredient Prices'!C16/1000*IF(E26="",0,E26),IF(D26="Oat",'💰 Ingredient Prices'!C17/1000*IF(E26="",0,E26),IF(D26="Almond",'💰 Ingredient Prices'!C18/1000*IF(E26="",0,E26),IF(D26="Soy",'💰 Ingredient Prices'!C19/1000*IF(E26="",0,E26),IF(D26="Coconut",'💰 Ingredient Prices'!C20/1000*IF(E26="",0,E26),0)))))))+IF(F26="",0,F26)*'💰 Ingredient Prices'!E26+(IF(G26="Small",'💰 Ingredient Prices'!C35+'💰 Ingredient Prices'!C38,IF(G26="Medium",'💰 Ingredient Prices'!C36+'💰 Ingredient Prices'!C38,IF(G26="Large",'💰 Ingredient Prices'!C37+'💰 Ingredient Prices'!C38,0)))+IF(H26="Y",'💰 Ingredient Prices'!C40,0))+IF(I26="",0,I26))
J27: =IF(B27="","",(IF(OR(B27="Batch brew / drip",B27="Cold brew"),'💰 Ingredient Prices'!C12,IF(C27="",0,C27)*'💰 Ingredient Prices'!C11))+(IF(D27="None",0,IF(D27="Dairy",'💰 Ingredient Prices'!C16/1000*IF(E27="",0,E27),IF(D27="Oat",'💰 Ingredient Prices'!C17/1000*IF(E27="",0,E27),IF(D27="Almond",'💰 Ingredient Prices'!C18/1000*IF(E27="",0,E27),IF(D27="Soy",'💰 Ingredient Prices'!C19/1000*IF(E27="",0,E27),IF(D27="Coconut",'💰 Ingredient Prices'!C20/1000*IF(E27="",0,E27),0)))))))+IF(F27="",0,F27)*'💰 Ingredient Prices'!E26+(IF(G27="Small",'💰 Ingredient Prices'!C35+'💰 Ingredient Prices'!C38,IF(G27="Medium",'💰 Ingredient Prices'!C36+'💰 Ingredient Prices'!C38,IF(G27="Large",'💰 Ingredient Prices'!C37+'💰 Ingredient Prices'!C38,0)))+IF(H27="Y",'💰 Ingredient Prices'!C40,0))+IF(I27="",0,I27))
J28: =IF(B28="","",(IF(OR(B28="Batch brew / drip",B28="Cold brew"),'💰 Ingredient Prices'!C12,IF(C28="",0,C28)*'💰 Ingredient Prices'!C11))+(IF(D28="None",0,IF(D28="Dairy",'💰 Ingredient Prices'!C16/1000*IF(E28="",0,E28),IF(D28="Oat",'💰 Ingredient Prices'!C17/1000*IF(E28="",0,E28),IF(D28="Almond",'💰 Ingredient Prices'!C18/1000*IF(E28="",0,E28),IF(D28="Soy",'💰 Ingredient Prices'!C19/1000*IF(E28="",0,E28),IF(D28="Coconut",'💰 Ingredient Prices'!C20/1000*IF(E28="",0,E28),0)))))))+IF(F28="",0,F28)*'💰 Ingredient Prices'!E26+(IF(G28="Small",'💰 Ingredient Prices'!C35+'💰 Ingredient Prices'!C38,IF(G28="Medium",'💰 Ingredient Prices'!C36+'💰 Ingredient Prices'!C38,IF(G28="Large",'💰 Ingredient Prices'!C37+'💰 Ingredient Prices'!C38,0)))+IF(H28="Y",'💰 Ingredient Prices'!C40,0))+IF(I28="",0,I28))
J29: =IF(B29="","",(IF(OR(B29="Batch brew / drip",B29="Cold brew"),'💰 Ingredient Prices'!C12,IF(C29="",0,C29)*'💰 Ingredient Prices'!C11))+(IF(D29="None",0,IF(D29="Dairy",'💰 Ingredient Prices'!C16/1000*IF(E29="",0,E29),IF(D29="Oat",'💰 Ingredient Prices'!C17/1000*IF(E29="",0,E29),IF(D29="Almond",'💰 Ingredient Prices'!C18/1000*IF(E29="",0,E29),IF(D29="Soy",'💰 Ingredient Prices'!C19/1000*IF(E29="",0,E29),IF(D29="Coconut",'💰 Ingredient Prices'!C20/1000*IF(E29="",0,E29),0)))))))+IF(F29="",0,F29)*'💰 Ingredient Prices'!E26+(IF(G29="Small",'💰 Ingredient Prices'!C35+'💰 Ingredient Prices'!C38,IF(G29="Medium",'💰 Ingredient Prices'!C36+'💰 Ingredient Prices'!C38,IF(G29="Large",'💰 Ingredient Prices'!C37+'💰 Ingredient Prices'!C38,0)))+IF(H29="Y",'💰 Ingredient Prices'!C40,0))+IF(I29="",0,I29))
J30: =IF(B30="","",(IF(OR(B30="Batch brew / drip",B30="Cold brew"),'💰 Ingredient Prices'!C12,IF(C30="",0,C30)*'💰 Ingredient Prices'!C11))+(IF(D30="None",0,IF(D30="Dairy",'💰 Ingredient Prices'!C16/1000*IF(E30="",0,E30),IF(D30="Oat",'💰 Ingredient Prices'!C17/1000*IF(E30="",0,E30),IF(D30="Almond",'💰 Ingredient Prices'!C18/1000*IF(E30="",0,E30),IF(D30="Soy",'💰 Ingredient Prices'!C19/1000*IF(E30="",0,E30),IF(D30="Coconut",'💰 Ingredient Prices'!C20/1000*IF(E30="",0,E30),0)))))))+IF(F30="",0,F30)*'💰 Ingredient Prices'!E26+(IF(G30="Small",'💰 Ingredient Prices'!C35+'💰 Ingredient Prices'!C38,IF(G30="Medium",'💰 Ingredient Prices'!C36+'💰 Ingredient Prices'!C38,IF(G30="Large",'💰 Ingredient Prices'!C37+'💰 Ingredient Prices'!C38,0)))+IF(H30="Y",'💰 Ingredient Prices'!C40,0))+IF(I30="",0,I30))
J31: =IF(B31="","",(IF(OR(B31="Batch brew / drip",B31="Cold brew"),'💰 Ingredient Prices'!C12,IF(C31="",0,C31)*'💰 Ingredient Prices'!C11))+(IF(D31="None",0,IF(D31="Dairy",'💰 Ingredient Prices'!C16/1000*IF(E31="",0,E31),IF(D31="Oat",'💰 Ingredient Prices'!C17/1000*IF(E31="",0,E31),IF(D31="Almond",'💰 Ingredient Prices'!C18/1000*IF(E31="",0,E31),IF(D31="Soy",'💰 Ingredient Prices'!C19/1000*IF(E31="",0,E31),IF(D31="Coconut",'💰 Ingredient Prices'!C20/1000*IF(E31="",0,E31),0)))))))+IF(F31="",0,F31)*'💰 Ingredient Prices'!E26+(IF(G31="Small",'💰 Ingredient Prices'!C35+'💰 Ingredient Prices'!C38,IF(G31="Medium",'💰 Ingredient Prices'!C36+'💰 Ingredient Prices'!C38,IF(G31="Large",'💰 Ingredient Prices'!C37+'💰 Ingredient Prices'!C38,0)))+IF(H31="Y",'💰 Ingredient Prices'!C40,0))+IF(I31="",0,I31))
J32: =IF(B32="","",(IF(OR(B32="Batch brew / drip",B32="Cold brew"),'💰 Ingredient Prices'!C12,IF(C32="",0,C32)*'💰 Ingredient Prices'!C11))+(IF(D32="None",0,IF(D32="Dairy",'💰 Ingredient Prices'!C16/1000*IF(E32="",0,E32),IF(D32="Oat",'💰 Ingredient Prices'!C17/1000*IF(E32="",0,E32),IF(D32="Almond",'💰 Ingredient Prices'!C18/1000*IF(E32="",0,E32),IF(D32="Soy",'💰 Ingredient Prices'!C19/1000*IF(E32="",0,E32),IF(D32="Coconut",'💰 Ingredient Prices'!C20/1000*IF(E32="",0,E32),0)))))))+IF(F32="",0,F32)*'💰 Ingredient Prices'!E26+(IF(G32="Small",'💰 Ingredient Prices'!C35+'💰 Ingredient Prices'!C38,IF(G32="Medium",'💰 Ingredient Prices'!C36+'💰 Ingredient Prices'!C38,IF(G32="Large",'💰 Ingredient Prices'!C37+'💰 Ingredient Prices'!C38,0)))+IF(H32="Y",'💰 Ingredient Prices'!C40,0))+IF(I32="",0,I32))
J33: =IF(B33="","",(IF(OR(B33="Batch brew / drip",B33="Cold brew"),'💰 Ingredient Prices'!C12,IF(C33="",0,C33)*'💰 Ingredient Prices'!C11))+(IF(D33="None",0,IF(D33="Dairy",'💰 Ingredient Prices'!C16/1000*IF(E33="",0,E33),IF(D33="Oat",'💰 Ingredient Prices'!C17/1000*IF(E33="",0,E33),IF(D33="Almond",'💰 Ingredient Prices'!C18/1000*IF(E33="",0,E33),IF(D33="Soy",'💰 Ingredient Prices'!C19/1000*IF(E33="",0,E33),IF(D33="Coconut",'💰 Ingredient Prices'!C20/1000*IF(E33="",0,E33),0)))))))+IF(F33="",0,F33)*'💰 Ingredient Prices'!E26+(IF(G33="Small",'💰 Ingredient Prices'!C35+'💰 Ingredient Prices'!C38,IF(G33="Medium",'💰 Ingredient Prices'!C36+'💰 Ingredient Prices'!C38,IF(G33="Large",'💰 Ingredient Prices'!C37+'💰 Ingredient Prices'!C38,0)))+IF(H33="Y",'💰 Ingredient Prices'!C40,0))+IF(I33="",0,I33))

Sheet 📊 Menu Summary
B2: Menu Summary
B3: Drink costs pull automatically from the Drink Builder. Add your selling price for each drink — margins calculate automatically.
B4: Green = pulled from Drink Builder | Blue = your selling price | Black = calculated
B6: Est. % of orders: estimate what share of your daily drink orders each item represents. All percentages should add up to 100%. This is used to calculate your weighted blended margin — the number that feeds back into your Week 2 financial model.
B7: Drink Name | C7: Cost per Drink ($) ← from Builder | D7: Selling Price ($) ← enter yours | E7: Margin per Drink ($) | F7: Margin % | G7: Est. % of All Orders | H7: Weighted Margin Contribution
B8: ='☕ Drink Builder'!B8 -> Espresso (single) | C8: =IF('☕ Drink Builder'!B8="","",IF('☕ Drink Builder'!J8="",0,'☕ Drink Builder'!J8)) -> 0.4698 | E8: =IF(OR(B8="",D8=""),"",D8-C8) | F8: =IF(OR(B8="",D8="",D8=0),"",E8/D8) | H8: =IF(OR(F8="",G8=""),"",F8*G8)
B9: ='☕ Drink Builder'!B9 -> Double espresso | C9: =IF('☕ Drink Builder'!B9="","",IF('☕ Drink Builder'!J9="",0,'☕ Drink Builder'!J9)) -> 0.7596 | E9: =IF(OR(B9="",D9=""),"",D9-C9) | F9: =IF(OR(B9="",D9="",D9=0),"",E9/D9) | H9: =IF(OR(F9="",G9=""),"",F9*G9)
B10: ='☕ Drink Builder'!B10 -> Macchiato | C10: =IF('☕ Drink Builder'!B10="","",IF('☕ Drink Builder'!J10="",0,'☕ Drink Builder'!J10)) -> 0.7956 | E10: =IF(OR(B10="",D10=""),"",D10-C10) | F10: =IF(OR(B10="",D10="",D10=0),"",E10/D10) | H10: =IF(OR(F10="",G10=""),"",F10*G10)
B11: ='☕ Drink Builder'!B11 -> Cortado | C11: =IF('☕ Drink Builder'!B11="","",IF('☕ Drink Builder'!J11="",0,'☕ Drink Builder'!J11)) -> 0.8316 | E11: =IF(OR(B11="",D11=""),"",D11-C11) | F11: =IF(OR(B11="",D11="",D11=0),"",E11/D11) | H11: =IF(OR(F11="",G11=""),"",F11*G11)
B12: ='☕ Drink Builder'!B12 -> Flat white | C12: =IF('☕ Drink Builder'!B12="","",IF('☕ Drink Builder'!J12="",0,'☕ Drink Builder'!J12)) -> 1.0456 | E12: =IF(OR(B12="",D12=""),"",D12-C12) | F12: =IF(OR(B12="",D12="",D12=0),"",E12/D12) | H12: =IF(OR(F12="",G12=""),"",F12*G12)
B13: ='☕ Drink Builder'!B13 -> Flat white (oat milk) | C13: =IF('☕ Drink Builder'!B13="","",IF('☕ Drink Builder'!J13="",0,'☕ Drink Builder'!J13)) -> 1.3336 | E13: =IF(OR(B13="",D13=""),"",D13-C13) | F13: =IF(OR(B13="",D13="",D13=0),"",E13/D13) | H13: =IF(OR(F13="",G13=""),"",F13*G13)
B14: ='☕ Drink Builder'!B14 -> Cappuccino | C14: =IF('☕ Drink Builder'!B14="","",IF('☕ Drink Builder'!J14="",0,'☕ Drink Builder'!J14)) -> 1.0456 | E14: =IF(OR(B14="",D14=""),"",D14-C14) | F14: =IF(OR(B14="",D14="",D14=0),"",E14/D14) | H14: =IF(OR(F14="",G14=""),"",F14*G14)
B15: ='☕ Drink Builder'!B15 -> Latte | C15: =IF('☕ Drink Builder'!B15="","",IF('☕ Drink Builder'!J15="",0,'☕ Drink Builder'!J15)) -> 1.1176 | E15: =IF(OR(B15="",D15=""),"",D15-C15) | F15: =IF(OR(B15="",D15="",D15=0),"",E15/D15) | H15: =IF(OR(F15="",G15=""),"",F15*G15)
B16: ='☕ Drink Builder'!B16 -> Latte (oat milk) | C16: =IF('☕ Drink Builder'!B16="","",IF('☕ Drink Builder'!J16="",0,'☕ Drink Builder'!J16)) -> 1.5016 | E16: =IF(OR(B16="",D16=""),"",D16-C16) | F16: =IF(OR(B16="",D16="",D16=0),"",E16/D16) | H16: =IF(OR(F16="",G16=""),"",F16*G16)
B17: ='☕ Drink Builder'!B17 -> Large latte | C17: =IF('☕ Drink Builder'!B17="","",IF('☕ Drink Builder'!J17="",0,'☕ Drink Builder'!J17)) -> 1.2096 | E17: =IF(OR(B17="",D17=""),"",D17-C17) | F17: =IF(OR(B17="",D17="",D17=0),"",E17/D17) | H17: =IF(OR(F17="",G17=""),"",F17*G17)
B18: ='☕ Drink Builder'!B18 -> Vanilla latte | C18: =IF('☕ Drink Builder'!B18="","",IF('☕ Drink Builder'!J18="",0,'☕ Drink Builder'!J18)) -> 1.2976 | E18: =IF(OR(B18="",D18=""),"",D18-C18) | F18: =IF(OR(B18="",D18="",D18=0),"",E18/D18) | H18: =IF(OR(F18="",G18=""),"",F18*G18)
B19: ='☕ Drink Builder'!B19 -> Batch brew / drip | C19: =IF('☕ Drink Builder'!B19="","",IF('☕ Drink Builder'!J19="",0,'☕ Drink Builder'!J19)) -> 0.547 | E19: =IF(OR(B19="",D19=""),"",D19-C19) | F19: =IF(OR(B19="",D19="",D19=0),"",E19/D19) | H19: =IF(OR(F19="",G19=""),"",F19*G19)
... B33: ='☕ Drink Builder'!B33 -> 0 | C33: =IF('☕ Drink Builder'!B33="","",IF('☕ Drink Builder'!J33="",0,'☕ Drink Builder'!J33)) | E33: =IF(OR(B33="",D33=""),"",D33-C33) | F33: =IF(OR(B33="",D33="",D33=0),"",E33/D33) | H33: =IF(OR(F33="",G33=""),"",F33*G33)
B34: TOTALS & BLENDED MARGIN | G34: =SUM(G8:G33) -> 0 | H34: =IFERROR(SUM(H8:H33),0) -> 0
B36: KEY METRICS
B37: Blended beverage margin | C37: =IFERROR(SUM(H8:H33),"-") -> 0 | D37: Target: 68–75%. If below 65%, review your pricing.
B38: Lowest margin drink | C38: =IFERROR(INDEX(B8:B33,MATCH(MIN(IF(F8:F33<>"",F8:F33)),F8:F33,0)),"-") -> - | D38: Watch this one — if it's a high-volume drink, it could drag down your blended margin.
B39: Highest margin drink | C39: =IFERROR(INDEX(B8:B33,MATCH(MAX(F8:F33),F8:F33,0)),"-") -> - | D39: Your most profitable drink — is it getting enough promotion?
B40: Drinks with margin below 65% | C40: =COUNTIF(F8:F33,"<0.65") -> 0 | D40: Any drink below 65% margin needs a pricing review.
B41: % of orders column sums to | C41: =SUM(G8:G33) -> 0 | D41: This should equal 100% before you trust the blended margin figure.
B43: BENCHMARK REMINDER
B44: Healthy target: Blended beverage margin 68–75% · Individual drink margin: ideally above 65% · Blended COGS (cost as % of revenue): 25–32% · Average ticket: $6–$10 for most café types. If your blended margin is below 65%, your prices are too low, your ingredient costs are too high, or both. Go back to your Ingredient Prices tab and check your actual costs — then check your menu prices against the benchmarks in the Week 4 Reference Sheet.
