Workbook

Sheet Start Here
B2: Equipment Checklist & Cost Estimator
B3: Coffee Shop Basecamp · Week 5 · Bar Layout & Equipment
B6: HOW TO USE THIS SHEET
B7: Step 1 — Equipment Checklist | C7: Go to the Equipment Checklist tab. Review each category and add any items specific to your shop.
B8: Step 2 — Enter your quotes | C8: For each item you need, enter the best price you found for New, Used, and/or Lease. Even rough estimates are useful at this stage.
B9: Step 3 — Choose your option | C9: In the 'Your choice' column, select New, Used, Lease, or N/A. The summary totals update automatically.
B10: Step 4 — Review the summary | C10: The Cost Summary tab shows your total opening equipment cost and monthly lease obligations. Compare this against your financial model from Week 2.
B13: COLOUR CODE: Blue text = your inputs Black text = calculated Yellow background = key inputs to fill in Blue-green background = standard inputs

Sheet Equipment Checklist
B2: Equipment Checklist & Cost Estimator — Week 5
B3: For each item you need, enter the best price you found for each option. Select your preferred option from the dropdown in column I. Yellow cells = your quotes to enter. Blue-green = other inputs.
B5: A — ESPRESSO BAR — CORE EQUIPMENT
B6: Equipment item | C6: Essential / Optional | D6: New — best price $ | E6: Used — best price $ | F6: Lease $/month | G6: Lease term (mo) | H6: Total lease cost $ | I6: Your choice | J6: Notes / supplier / source
B7: Commercial espresso machine (2-group) | C7: Essential | H7: =IFERROR(IF(F7="","",F7*G7),"") | I7: TBD | J7: La Marzocco, Synesso, Victoria Arduino, Sanremo. 2-group standard, 3-group for high volume. Get a quote for new and ask dealers about used / ex-lease.
B8: Commercial espresso grinder — House blend | C8: Essential | H8: =IFERROR(IF(F8="","",F8*G8),"") | I8: TBD | J8: Mahlkonig EK43S, Mythos One, Eureka Atom. Budget for a second grinder if serving single origin or decaf.
B9: Commercial espresso grinder — Single origin / decaf | C9: Essential | H9: =IFERROR(IF(F9="","",F9*G9),"") | I9: TBD | J9: Same brands. Having two grinders avoids re-dialling between coffees during service — critical for quality and speed.
B10: Underbench milk fridge | C10: Essential | H10: =IFERROR(IF(F10="","",F10*G10),"") | I10: TBD | J10: Commercial refrigeration below or adjacent to steam wand. Must reach and hold <4C. Check depth and litre capacity against peak service milk volume.
B11: Water filtration system | C11: Essential | H11: =IFERROR(IF(F11="","",F11*G11),"") | I11: TBD | J11: BWT, Pentair, or roaster-recommended system. Protects machine, improves flavour. Factor in ongoing filter cartridge costs (typically annual).
B12: Knock box — built-in or mounted | C12: Essential | H12: =IFERROR(IF(F12="","",F12*G12),"") | I12: TBD | J12: Built-in bench knock box preferred. Freestanding knock boxes shift during use. Position directly at the barista's working position.
B13: Tamper (calibrated) | C13: Essential | H13: =IFERROR(IF(F13="","",F13*G13),"") | I13: TBD | J13: 58.5mm for most commercial machines. Calibrated tamper gives consistent pressure. Budget $80–$200.
B14: Distribution tool / WDT | C14: Optional | H14: =IFERROR(IF(F14="","",F14*G14),"") | I14: TBD | J14: Improves shot-to-shot consistency. Increasingly standard in specialty cafes. Budget $80–$200.
B15: Milk pitchers — assorted sizes | C15: Essential | H15: =IFERROR(IF(F15="","",F15*G15),"") | I15: TBD | J15: 300ml, 600ml, and 1L minimum. Buy at least 2 of each. Stainless steel. Budget $20–$40 each.
B16: Milk thermometers | C16: Essential | H16: =IFERROR(IF(F16="","",F16*G16),"") | I16: TBD | J16: For training and consistency. Waterproof digital preferred. Budget $15–$30 each. Buy 3–4.
H17: =IFERROR(IF(F17="","",F17*G17),"") | I17: TBD
H18: =IFERROR(IF(F18="","",F18*G18),"") | I18: TBD
H19: =IFERROR(IF(F19="","",F19*G19),"") | I19: TBD
B20: Section A subtotal | D20: =IFERROR(SUMIF(I7:I19,"<>N/A",D7:D19),0) -> 0 | E20: =IFERROR(SUMIF(I7:I19,"<>N/A",E7:E19),0) -> 0 | H20: =IFERROR(SUMIF(I7:I19,"<>N/A",H7:H19),0) -> 0
B22: B — FILTER & COLD DRINKS
B23: Equipment item | C23: Essential / Optional | D23: New — best price $ | E23: Used — best price $ | F23: Lease $/month | G23: Lease term (mo) | H23: Total lease cost $ | I23: Your choice | J23: Notes / supplier / source
B24: Commercial batch brewer (Fetco, Marco, or similar) | C24: Essential | H24: =IFERROR(IF(F24="","",F24*G24),"") | I24: TBD | J24: If serving batch brew — which is your highest-margin drink. Must hold temp without continuing to cook. Budget $2,500–$5,000 new.
B25: Filter grinder (if pour-over on menu) | C25: Optional | H25: =IFERROR(IF(F25="","",F25*G25),"") | I25: TBD | J25: Separate grinder for filter grind sizes. Mahlkonig EK43 is industry standard. Only needed if you're serving manual pour-over.
B26: Pour-over station, kettle, scales | C26: Optional | H26: =IFERROR(IF(F26="","",F26*G26),"") | I26: TBD | J26: Gooseneck electric kettle, precision scales (0.1g), dripper and server. Only if pour-over is on the menu. Adds time per drink — factor into workflow.
B27: Cold brew brewing vessel + storage | C27: Optional | H27: =IFERROR(IF(F27="","",F27*G27),"") | I27: TBD | J27: Large stainless brewing vessel (10–20L) plus refrigerated storage. If cold brew is on your menu. Brew time 12–18 hours — plan accordingly.
B28: Commercial blender (Vitamix, Blendtec) | C28: Optional | H28: =IFERROR(IF(F28="","",F28*G28),"") | I28: TBD | J28: Only if serving blended drinks. Needs dedicated counter space and ventilation consideration for noise. Budget $800–$1,500 commercial grade.
B29: Ice machine or ice supply arrangement | C29: Optional | H29: =IFERROR(IF(F29="","",F29*G29),"") | I29: TBD | J29: If serving iced drinks at volume. Commercial ice machines are expensive — many operators use a bag ice delivery service initially.
H30: =IFERROR(IF(F30="","",F30*G30),"") | I30: TBD
H31: =IFERROR(IF(F31="","",F31*G31),"") | I31: TBD
B32: Section B subtotal | D32: =IFERROR(SUMIF(I24:I31,"<>N/A",D24:D31),0) -> 0 | E32: =IFERROR(SUMIF(I24:I31,"<>N/A",E24:E31),0) -> 0 | H32: =IFERROR(SUMIF(I24:I31,"<>N/A",H24:H31),0) -> 0
B34: C — FOOD EQUIPMENT (if offering food)
B35: Equipment item | C35: Essential / Optional | D35: New — best price $ | E35: Used — best price $ | F35: Lease $/month | G35: Lease term (mo) | H35: Total lease cost $ | I35: Your choice | J35: Notes / supplier / source
B36: Commercial display cabinet / pastry case | C36: Optional | H36: =IFERROR(IF(F36="","",F36*G36),"") | I36: TBD | J36: For displaying baked goods. Refrigerated or ambient depending on your food. Consider size relative to your daily pastry volume.
B37: Commercial toaster or panini press | C37: Optional | H37: =IFERROR(IF(F37="","",F37*G37),"") | I37: TBD | J37: If heating food to order. Check local food handling regulations — heating may require additional compliance.
B38: Commercial food fridge (underbench) | C38: Optional | H38: =IFERROR(IF(F38="","",F38*G38),"") | I38: TBD | J38: Separate from milk fridge if food storage volume requires it. Factor in temperature zoning requirements.
B39: Food prep bench / surfaces | C39: Optional | H39: =IFERROR(IF(F39="","",F39*G39),"") | I39: TBD | J39: If making food in-house. Must meet local food handling standards — stainless preferred. Check certification requirements in your area.
H40: =IFERROR(IF(F40="","",F40*G40),"") | I40: TBD
H41: =IFERROR(IF(F41="","",F41*G41),"") | I41: TBD
B42: Section C subtotal | D42: =IFERROR(SUMIF(I36:I41,"<>N/A",D36:D41),0) -> 0 | E42: =IFERROR(SUMIF(I36:I41,"<>N/A",E36:E41),0) -> 0 | H42: =IFERROR(SUMIF(I36:I41,"<>N/A",H36:H41),0) -> 0
B44: D — TECHNOLOGY & POINT OF SALE
B45: Equipment item | C45: Essential / Optional | D45: New — best price $ | E45: Used — best price $ | F45: Lease $/month | G45: Lease term (mo) | H45: Total lease cost $ | I45: Your choice | J45: Notes / supplier / source
B46: POS system — hardware (tablet/screen + stand) | C46: Essential | H46: =IFERROR(IF(F46="","",F46*G46),"") | I46: TBD | J46: Square, Lightspeed, Kounta, H&L, or similar. Factor in monthly subscription cost separately. Check payment terminal compatibility.
B47: Payment terminal (EFTPOS / card reader) | C47: Essential | H47: =IFERROR(IF(F47="","",F47*G47),"") | I47: TBD | J47: Check if bundled with your POS. Flat-rate or %-based processing fees — factor into your margin calculations from Week 2.
B48: Receipt printer (thermal) | C48: Essential | H48: =IFERROR(IF(F48="","",F48*G48),"") | I48: TBD | J48: Epson TM series is standard. Wired or wireless — wireless requires reliable Wi-Fi. Budget $200–$400.
B49: Kitchen / bar order printer | C49: Optional | H49: =IFERROR(IF(F49="","",F49*G49),"") | I49: TBD | J49: If your workflow uses printed drink tickets. Useful if volume is high enough that calling orders becomes impractical.
B50: Customer display screen | C50: Optional | H50: =IFERROR(IF(F50="","",F50*G50),"") | I50: TBD | J50: Shows customer their order and total. Improves order accuracy. More relevant for higher-volume operations.
H51: =IFERROR(IF(F51="","",F51*G51),"") | I51: TBD
H52: =IFERROR(IF(F52="","",F52*G52),"") | I52: TBD
B53: Section D subtotal | D53: =IFERROR(SUMIF(I46:I52,"<>N/A",D46:D52),0) -> 0 | E53: =IFERROR(SUMIF(I46:I52,"<>N/A",E46:E52),0) -> 0 | H53: =IFERROR(SUMIF(I46:I52,"<>N/A",H46:H52),0) -> 0
B55: E — BACK OF HOUSE & UTILITIES
B56: Equipment item | C56: Essential / Optional | D56: New — best price $ | E56: Used — best price $ | F56: Lease $/month | G56: Lease term (mo) | H56: Total lease cost $ | I56: Your choice | J56: Notes / supplier / source
B57: Commercial underbench glasswasher / dishwasher | C57: Essential | H57: =IFERROR(IF(F57="","",F57*G57),"") | I57: TBD | J57: Essential for sit-down cafes. For takeaway-heavy operations, assess actual cup/vessel volume. Budget $2,000–$5,000 new.
B58: Three-compartment sink | C58: Essential | H58: =IFERROR(IF(F58="","",F58*G58),"") | I58: TBD | J58: Required in most jurisdictions for wash / rinse / sanitise. Check your local food safety compliance requirements.
B59: Hand wash basin (dedicated) | C59: Essential | H59: =IFERROR(IF(F59="","",F59*G59),"") | I59: TBD | J59: Separate from the main sink in most markets. Check local environmental health requirements before finalising layout.
B60: 3-phase electrical installation | C60: Essential | H60: =IFERROR(IF(F60="","",F60*G60),"") | I60: TBD | J60: Commercial espresso machines require 3-phase in most markets. Must be confirmed before finalising bar position. Get an electrician in early.
B61: Plumbing — drain lines, water supply | C61: Essential | H61: =IFERROR(IF(F61="","",F61*G61),"") | I61: TBD | J61: Cost varies significantly depending on distance from existing services. This is one of the most common sources of fit-out budget overruns.
B62: Commercial ventilation / exhaust (if applicable) | C62: Optional | H62: =IFERROR(IF(F62="","",F62*G62),"") | I62: TBD | J62: If offering hot food or using commercial cooking equipment. Check local requirements — ventilation can be a significant cost.
B63: Security system (alarm, CCTV) | C63: Optional | H63: =IFERROR(IF(F63="","",F63*G63),"") | I63: TBD | J63: Usually required by commercial insurance. Get a quote as part of your pre-opening budget, not as an afterthought.
H64: =IFERROR(IF(F64="","",F64*G64),"") | I64: TBD
H65: =IFERROR(IF(F65="","",F65*G65),"") | I65: TBD
B66: Section E subtotal | D66: =IFERROR(SUMIF(I57:I65,"<>N/A",D57:D65),0) -> 0 | E66: =IFERROR(SUMIF(I57:I65,"<>N/A",E57:E65),0) -> 0 | H66: =IFERROR(SUMIF(I57:I65,"<>N/A",H57:H65),0) -> 0
B68: F — FURNITURE, FIXTURES & FIT-OUT
B69: Equipment item | C69: Essential / Optional | D69: New — best price $ | E69: Used — best price $ | F69: Lease $/month | G69: Lease term (mo) | H69: Total lease cost $ | I69: Your choice | J69: Notes / supplier / source
B70: Bar / counter construction and joinery | C70: Essential | H70: =IFERROR(IF(F70="","",F70*G70),"") | I70: TBD | J70: Usually the biggest single fit-out line item. Get at least three quotes. Factor in bench material, underbench storage, and equipment cut-outs.
B71: Customer seating — chairs | C71: Optional | H71: =IFERROR(IF(F71="","",F71*G71),"") | I71: TBD | J71: Depends on your shop model. Grab-and-go may need none. Neighbourhood café typically 20–40 chairs. Commercial-grade durability essential.
B72: Customer tables | C72: Optional | H72: =IFERROR(IF(F72="","",F72*G72),"") | I72: TBD | J72: As above. Factor in table size vs. covers capacity. Outdoor tables if applicable — check council requirements.
B73: Menu board(s) | C73: Essential | H73: =IFERROR(IF(F73="","",F73*G73),"") | I73: TBD | J73: Chalkboard, printed, or digital. Must be readable from at least 3m back in the queue. Factor in update costs for seasonal menus.
B74: Lighting — bar and customer areas | C74: Essential | H74: =IFERROR(IF(F74="","",F74*G74),"") | I74: TBD | J74: Lighting significantly affects atmosphere and staff working conditions. Get a lighting plan done as part of the fit-out, not as an afterthought.
B75: Signage — exterior and interior | C75: Essential | H75: =IFERROR(IF(F75="","",F75*G75),"") | I75: TBD | J75: Exterior signage often requires council approval. Factor in lead times — signage delays can hold up opening.
H76: =IFERROR(IF(F76="","",F76*G76),"") | I76: TBD
H77: =IFERROR(IF(F77="","",F77*G77),"") | I77: TBD
B78: Section F subtotal | D78: =IFERROR(SUMIF(I70:I77,"<>N/A",D70:D77),0) -> 0 | E78: =IFERROR(SUMIF(I70:I77,"<>N/A",E70:E77),0) -> 0 | H78: =IFERROR(SUMIF(I70:I77,"<>N/A",H70:H77),0) -> 0

Sheet Cost Summary
B2: Equipment Cost Summary
B3: This summary pulls from your Equipment Checklist automatically. It shows your total opening equipment cost based on the options you've selected.
B6: Category | C6: If all new | D6: If all used | E6: If all leased (total)
B7: A — Espresso Bar Core | C7: =IFERROR(SUMIF('Equipment Checklist'!I:I,"New",'Equipment Checklist'!D:D),0) -> 0 | D7: =IFERROR(SUMIF('Equipment Checklist'!I:I,"Used",'Equipment Checklist'!E:E),0) -> 0 | E7: =IFERROR(SUMIF('Equipment Checklist'!I:I,"Lease",'Equipment Checklist'!H:H),0) -> 0
B8: B — Filter & Cold Drinks | C8: =IFERROR(SUMIF('Equipment Checklist'!I:I,"New",'Equipment Checklist'!D:D),0) -> 0 | D8: =IFERROR(SUMIF('Equipment Checklist'!I:I,"Used",'Equipment Checklist'!E:E),0) -> 0 | E8: =IFERROR(SUMIF('Equipment Checklist'!I:I,"Lease",'Equipment Checklist'!H:H),0) -> 0
B9: C — Food Equipment | C9: =IFERROR(SUMIF('Equipment Checklist'!I:I,"New",'Equipment Checklist'!D:D),0) -> 0 | D9: =IFERROR(SUMIF('Equipment Checklist'!I:I,"Used",'Equipment Checklist'!E:E),0) -> 0 | E9: =IFERROR(SUMIF('Equipment Checklist'!I:I,"Lease",'Equipment Checklist'!H:H),0) -> 0
B10: D — Technology & POS | C10: =IFERROR(SUMIF('Equipment Checklist'!I:I,"New",'Equipment Checklist'!D:D),0) -> 0 | D10: =IFERROR(SUMIF('Equipment Checklist'!I:I,"Used",'Equipment Checklist'!E:E),0) -> 0 | E10: =IFERROR(SUMIF('Equipment Checklist'!I:I,"Lease",'Equipment Checklist'!H:H),0) -> 0
B11: E — Back of House | C11: =IFERROR(SUMIF('Equipment Checklist'!I:I,"New",'Equipment Checklist'!D:D),0) -> 0 | D11: =IFERROR(SUMIF('Equipment Checklist'!I:I,"Used",'Equipment Checklist'!E:E),0) -> 0 | E11: =IFERROR(SUMIF('Equipment Checklist'!I:I,"Lease",'Equipment Checklist'!H:H),0) -> 0
B12: F — Furniture & Fit-Out | C12: =IFERROR(SUMIF('Equipment Checklist'!I:I,"New",'Equipment Checklist'!D:D),0) -> 0 | D12: =IFERROR(SUMIF('Equipment Checklist'!I:I,"Used",'Equipment Checklist'!E:E),0) -> 0 | E12: =IFERROR(SUMIF('Equipment Checklist'!I:I,"Lease",'Equipment Checklist'!H:H),0) -> 0
B13: TOTAL SELECTED EQUIPMENT COST | C13: =C7+C8+C9+C10+C11+C12 -> 0 | D13: =D7+D8+D9+D10+D11+D12 -> 0 | E13: =E7+E8+E9+E10+E11+E12 -> 0
B15: MONTHLY LEASE OBLIGATIONS (for leased items)
B16: Total monthly lease payments | E16: =IFERROR(SUMIF('Equipment Checklist'!I:I,"Lease",'Equipment Checklist'!F:F),0) -> 0
B18: BENCHMARKS & HONEST NOTES
B19: Typical small café equipment budget | C19: $30,000 – $80,000+ | D19: Highly variable depending on whether buying new/used, machine quality, and fit-out scope. This is capital expenditure only — not including fit-out and build costs.
B20: Espresso machine alone (new, 2-group) | C20: $12,000 – $25,000 | D20: This is often the single largest equipment line item. A used machine from a reputable dealer ($4,000–$10,000) can significantly reduce this.
B21: Does your equipment total fit your opening budget? | C21: Compare with Week 2 | D21: Go back to your financial model. If your equipment total exceeds your available capital, you need to revisit what you're buying new vs. used vs. leasing.
